facebook_feed_sync/__init__.py
facebook_feed_sync/__main__.py
facebook_feed_sync/cli.py
facebook_feed_sync/packages/__init__.py
facebook_feed_sync/packages/gsheet.py
facebook_feed_sync/packages/plenty.py
facebook_feed_sync/packages/shared_data.py
facebook_feed_sync-0.2.1.dist-info/LICENSE
facebook_feed_sync-0.2.1.dist-info/WHEEL
facebook_feed_sync-0.2.1.dist-info/METADATA
facebook_feed_sync-0.2.1.dist-info/RECORD
