Metadata-Version: 2.1
Name: facebook-feed-sync
Version: 0.2.1
Summary: Lightweight connector of PlentyMarkets to Facebook Catalogs via a google-spreadsheet. Update product information regulary and import data to facebook.
Home-page: https://github.com/initBasti/
License: GPL-3.0-or-later
Keywords: plentymarkets,python,facebook,googlesheet,connector
Author: Sebastian Fricke
Author-email: sebastian.fricke.linux@gmail.com
Requires-Python: >=3.7,<4.0
Classifier: Development Status :: 1 - Planning
Classifier: License :: OSI Approved :: GNU General Public License v3 or later (GPLv3+)
Classifier: Natural Language :: English
Classifier: Operating System :: OS Independent
Classifier: Programming Language :: Python
Classifier: Programming Language :: Python :: 3
Classifier: Programming Language :: Python :: 3.7
Classifier: Programming Language :: Python :: 3.8
Requires-Dist: gspread (>=3.6.0,<4.0.0)
Requires-Dist: gspread-dataframe (>=3.1.1,<4.0.0)
Requires-Dist: loguru (>=0.5.3,<0.6.0)
Requires-Dist: pandas (>=1.1.3,<2.0.0)
Requires-Dist: plenty_api (>=0.2.7,<0.3.0)
Requires-Dist: pytest_describe (>=1.0.0,<2.0.0)
Requires-Dist: pytest_mock (>=3.3.1,<4.0.0)
Requires-Dist: pytest_sugar (>=0.9.4,<0.10.0)
Project-URL: Repository, https://github.com/initBasti/
